{"cpuTimeFrame":27367,"cpuTimeBegin":131572958300,"cpuTimeEnd":131572958404,"cpuTimerFreq":10000000,"gpuTimeBegin":1633687737569942200,"gpuTimeEnd":1633687737569942200,"gpuTimerFreq":1000000000,"waitRender":0,"waitSubmit":0,"numDraw":0,"numCompute":0,"numBlit":0,"maxGpuLatency":64,"numDynamicIndexBuffers":0,"numDynamicVertexBuffers":0,"numFrameBuffers":0,"numIndexBuffers":4,"numOcclusionQueries":0,"numPrograms":60,"numShaders":100,"numTextures":2,"numUniforms":148,"numVertexBuffers":6,"numVertexLayouts":5,"textureMemoryUsed":311296,"rtMemoryUsed":0,"transientVbUsed":0,"transientIbUsed":0,"gpuMemoryMax":4154458112,"gpuMemoryUsed":1573593088,"numViews":0}